document_renaming/__init__.py
document_renaming/admin.py
document_renaming/apps.py
document_renaming/handlers.py
document_renaming/links.py
document_renaming/literals.py
document_renaming/managers.py
document_renaming/models.py
document_renaming/permissions.py
document_renaming/tasks.py
document_renaming/urls.py
document_renaming/views.py
document_renaming/migrations/0001_initial.py
document_renaming/migrations/0002_sequence_increment.py
document_renaming/migrations/0003_auto_20151220_0717.py
document_renaming/migrations/0004_auto_20151220_0751.py
document_renaming/migrations/0005_auto_20151221_0402.py
document_renaming/migrations/0006_auto_20151221_0402.py
document_renaming/migrations/__init__.py
document_renaming/tests/__init__.py
document_renaming/tests/literals.py
document_renaming/tests/test_models.py
document_renaming/tests/test_views.py
mayan_document_renaming-1.0.0.dist-info/DESCRIPTION.rst
mayan_document_renaming-1.0.0.dist-info/METADATA
mayan_document_renaming-1.0.0.dist-info/RECORD
mayan_document_renaming-1.0.0.dist-info/WHEEL
mayan_document_renaming-1.0.0.dist-info/metadata.json
mayan_document_renaming-1.0.0.dist-info/top_level.txt
