Metadata-Version: 2.0
Name: mayan-document-renaming
Version: 1.0.0
Summary: Automatic document renaming app for Mayan EDMS.
Home-page: https://gitlab.com/mayan-edms/document_renaming
Author: Roberto Rosario
Author-email: roberto.rosario@mayan-edms.com
License: The MIT License (MIT)
